{
  "Tipo": "Jupiter_III",
  "Titulo": "imagenes/Nantsune/Jupiter logo.png",
  "Video": "url_video_1.mp4",
  "Imagen": "imagenes/Nantsune/HUPITER-III.png",
  "ImagenDimension": "url_imagen_elemento1.jpg",
  "Caracteristicas": [
    {
      "Texto": "Panel táctil para su fácil operación y ordenamiento por grupos de rebanadas."
    },
    {
      "Texto": "Cortadora de alta producción con doble cuchilla circular."
    },
    {
      "Texto": "Se puede rebanar material de 340 mm de ancho,180 mm de altura y 600 mm de largo a temperatura entre -2°C a 4°C."
    },
    {
      "Texto": "Se puede apilar los cortes en efecto domino y separarlos en grupos."
    },
    {
      "Texto": "Realiza hasta 320 cortes por minuto con juste en grosor de 0.1 a 40 mm."
    },
    {
      "Texto": "Cuenta con banda trasportadora para facilitar el empaque final en charola o plato."
    },
    {
      "Texto": "No requiere herramienta especializada para su limpieza."
    }
  ],
  "Espesor": []
}